flask_user/__init__.py
flask_user/adapters.py
flask_user/blueprint.py
flask_user/database.py
flask_user/domain.py
flask_user/forms.py
flask_user/models.py
flask_user/repositories.py
flask_user/utils.py
flask_user/views.py
flask_user/extensions/__init__.py
flask_user/extensions/login.py
tests/__init__.py
flask_user_utils-1.2.0.dist-info/LICENSE
flask_user_utils-1.2.0.dist-info/METADATA
flask_user_utils-1.2.0.dist-info/WHEEL
flask_user_utils-1.2.0.dist-info/top_level.txt
flask_user_utils-1.2.0.dist-info/RECORD
