Metadata-Version: 2.1
Name: flask-user-utils
Version: 1.2.0
License-File: LICENSE
Requires-Dist: Flask
Requires-Dist: SQLAlchemy
Requires-Dist: dynaconf
Requires-Dist: python-dotenv
Requires-Dist: Flask-Login
Requires-Dist: psycopg2
Requires-Dist: Flask-WTF
